{"format": "torch", "nodes": [{"name": "site_embedding", "id": 140416241852128, "class_name": "Embedding(24, 64, max_norm=True)", "parameters": [["weight", [24, 64]]], "output_shape": [[512, 1, 64]], "num_parameters": [1536]}, {"name": "flatten", "id": 140416241850544, "class_name": "Flatten(start_dim=1, end_dim=-1)", "parameters": [], "output_shape": [[512, 64]], "num_parameters": []}, {"name": "fixed_bssid.0", "id": 140416241848960, "class_name": "BatchNorm1d(50, eps=1e-05, momentum=0.1, affine=True, track_running_stats=True)", "parameters": [["weight", [50]], ["bias", [50]]], "output_shape": [[512, 50]], "num_parameters": [50, 50]}, {"name": "fixed_bssid.1", "id": 140416241850256, "class_name": "Linear(in_features=50, out_features=3200, bias=True)", "parameters": [["weight", [3200, 50]], ["bias", [3200]]], "output_shape": [[512, 3200]], "num_parameters": [160000, 3200]}, {"name": "bn1", "id": 140416241849728, "class_name": "BatchNorm1d(3264, eps=1e-05, momentum=0.1, affine=True, track_running_stats=True)", "parameters": [["weight", [3264]], ["bias", [3264]]], "output_shape": [[512, 3264]], "num_parameters": [3264, 3264]}, {"name": "dropout1", "id": 140416241850784, "class_name": "Dropout(p=0.3, inplace=False)", "parameters": [], "output_shape": [[512, 3264]], "num_parameters": []}, {"name": "linear1", "id": 140416241848528, "class_name": "Linear(in_features=3264, out_features=256, bias=True)", "parameters": [["weight", [256, 3264]], ["bias", [256]]], "output_shape": [[512, 256]], "num_parameters": [835584, 256]}, {"name": "bn2", "id": 140416241848480, "class_name": "BatchNorm1d(256, eps=1e-05, momentum=0.1, affine=True, track_running_stats=True)", "parameters": [["weight", [256]], ["bias", [256]]], "output_shape": [[512, 256]], "num_parameters": [256, 256]}, {"name": "linear2", "id": 140416401139168, "class_name": "Linear(in_features=256, out_features=128, bias=True)", "parameters": [["weight", [128, 256]], ["bias", [128]]], "output_shape": [[512, 128]], "num_parameters": [32768, 128]}, {"name": "bn3", "id": 140416401137968, "class_name": "BatchNorm1d(128, eps=1e-05, momentum=0.1, affine=True, track_running_stats=True)", "parameters": [["weight", [128]], ["bias", [128]]], "output_shape": [[512, 128]], "num_parameters": [128, 128]}, {"name": "linear3", "id": 140416401138064, "class_name": "Linear(in_features=128, out_features=16, bias=True)", "parameters": [["weight", [16, 128]], ["bias", [16]]], "output_shape": [[512, 16]], "num_parameters": [2048, 16]}, {"name": "bn4", "id": 140416401141136, "class_name": "BatchNorm1d(16, eps=1e-05, momentum=0.1, affine=True, track_running_stats=True)", "parameters": [["weight", [16]], ["bias", [16]]], "output_shape": [[512, 16]], "num_parameters": [16, 16]}, {"name": "xy", "id": 140416401138256, "class_name": "Linear(in_features=16, out_features=2, bias=True)", "parameters": [["weight", [2, 16]], ["bias", [2]]], "output_shape": [[512, 2]], "num_parameters": [32, 2]}, {"name": "floor", "id": 140416401138112, "class_name": "Linear(in_features=16, out_features=1, bias=True)", "parameters": [["weight", [1, 16]], ["bias", [1]]], "output_shape": [[512, 1]], "num_parameters": [16, 1]}], "edges": []}